interaction_discord_bot/__init__.py
interaction_discord_bot/init_cog.py
interaction_discord_bot/cogs/__init__.py
interaction_discord_bot/cogs/message.py
interaction_discord_bot/modal/__init__.py
interaction_discord_bot/modal/replyModal.py
interaction_discord_bot/modal/speakModal.py
interaction_discord_bot/modal/updateModal.py
interaction_discord_bot/utils/__init__.py
interaction_discord_bot/utils/message.py
interaction_discord_bot-0.2.0.dist-info/METADATA
interaction_discord_bot-0.2.0.dist-info/WHEEL
interaction_discord_bot-0.2.0.dist-info/top_level.txt
interaction_discord_bot-0.2.0.dist-info/RECORD
