Metadata-Version: 2.2
Name: interaction_discord_bot
Version: 0.2.0
Summary: cog for discord bot interaction with user
Author: Appez
Requires-Dist: nextcord
Dynamic: author
Dynamic: requires-dist
Dynamic: summary
